dashub/__init__.py
dashub/apps.py
dashub/compat.py
dashub/fields.py
dashub/serializer.py
dashub/settings.py
dashub/utils.py
dashub/widgets.py
dashub/contrib/filters.py
dashub/contrib/forms.py
dashub/contrib/mixins.py
dashub/static/admin/img/icon-addlink.svg
dashub/static/admin/img/icon-changelink.svg
dashub/static/admin/img/icon-deletelink.svg
dashub/static/admin/img/icon-no.svg
dashub/static/admin/img/icon-viewlink.svg
dashub/static/admin/img/icon-yes.svg
dashub/static/admin/js/cancel.js
dashub/static/admin/js/popup_response.js
dashub/static/assets/css/login.css
dashub/static/assets/css/style.css
dashub/static/assets/css/theme.css
dashub/static/assets/css/tinymce.css
dashub/static/assets/img/login.avif
dashub/static/assets/img/selector-icons.svg
dashub/static/assets/img/user.png
dashub/static/assets/img/user.svg
dashub/static/assets/js/change_form.js
dashub/static/assets/js/main.js
dashub/static/assets/js/related-modal.js
dashub/static/assets/js/select2.init.js
dashub/static/assets/plugins/bootstrap-show-modal/bootstrap-show-modal.min.js
dashub/templates/admin/actions.html
dashub/templates/admin/app_index.html
dashub/templates/admin/base.html
dashub/templates/admin/base_site.html
dashub/templates/admin/change_form.html
dashub/templates/admin/change_form_object_tools.html
dashub/templates/admin/change_list.html
dashub/templates/admin/change_list_object_tools.html
dashub/templates/admin/change_list_results.html
dashub/templates/admin/date_hierarchy.html
dashub/templates/admin/delete_confirmation.html
dashub/templates/admin/delete_selected_confirmation.html
dashub/templates/admin/filter.html
dashub/templates/admin/index.html
dashub/templates/admin/login.html
dashub/templates/admin/mptt_filter.html
dashub/templates/admin/object_history.html
dashub/templates/admin/pagination.html
dashub/templates/admin/popup_response.html
dashub/templates/admin/search_form.html
dashub/templates/admin/submit_line.html
dashub/templates/admin/auth/user/add_form.html
django_dashub-3.0.7.dist-info/AUTHORS
django_dashub-3.0.7.dist-info/LICENSE
django_dashub-3.0.7.dist-info/METADATA
django_dashub-3.0.7.dist-info/WHEEL
django_dashub-3.0.7.dist-info/top_level.txt
django_dashub-3.0.7.dist-info/RECORD
