Metadata-Version: 2.1
Name: django_dashub
Version: 3.0.7
Summary: A modern Django admin dashboard with enhanced customization options, inspired by Jazzmin but featuring a fresh theme and additional functionality.
Author: Suresh Chand
Author-email: scthakuri12a@gmail.com
License: BSD
Project-URL: Bug Reports, https://github.com/scthakuri/django-dashub/issues
Project-URL: Source, https://github.com/scthakuri/django-dashub
Classifier: Programming Language :: Python :: 3
Classifier: Framework :: Django
Classifier: Environment :: Web Environment
Classifier: Intended Audience :: Developers
Classifier: Operating System :: OS Independent
Classifier: Development Status :: 5 - Production/Stable
Classifier: License :: OSI Approved :: BSD License
License-File: LICENSE
License-File: AUTHORS
Requires-Dist: django
